altkinter/__init__.py
altkinter/altk.py
altkinter/button.py
altkinter/check_button.py
altkinter/combobox.py
altkinter/entry.py
altkinter/fonts.py
altkinter/label.py
altkinter/listbox.py
altkinter/progress_window.py
altkinter/progressbar.py
altkinter/scrollbar.py
altkinter/tableview.py
altkinter/theme.py
altkinter/tooltip.py
altkinter-0.1.0.dist-info/METADATA
altkinter-0.1.0.dist-info/WHEEL
altkinter-0.1.0.dist-info/top_level.txt
altkinter-0.1.0.dist-info/RECORD
