Metadata-Version: 2.4
Name: altkinter
Version: 0.1.0
Summary: A modern Tkinter widget library with custom themes and controls.
Home-page: https://github.com/odukle/altkinter
Author: Saurabh Odukle
Author-email: odukle@gmail.com
License: MIT
Classifier: Programming Language :: Python :: 3
Classifier: License :: OSI Approved :: MIT License
Classifier: Operating System :: OS Independent
Requires-Python: >=3.7
Requires-Dist: Pillow
Requires-Dist: pycairo
Dynamic: author
Dynamic: author-email
Dynamic: classifier
Dynamic: home-page
Dynamic: license
Dynamic: requires-dist
Dynamic: requires-python
Dynamic: summary
